docker_xylem/__init__.py
docker_xylem/compat.py
docker_xylem/service.py
docker_xylem/utils.py
docker_xylem/tests/__init__.py
docker_xylem/tests/test_docker_xylem.py
docker_xylem-0.1.9.dist-info/DESCRIPTION.rst
docker_xylem-0.1.9.dist-info/METADATA
docker_xylem-0.1.9.dist-info/metadata.json
docker_xylem-0.1.9.dist-info/RECORD
docker_xylem-0.1.9.dist-info/top_level.txt
docker_xylem-0.1.9.dist-info/WHEEL
twisted/plugins/docker_xylem_plugin.py
