Metadata-Version: 2.0
Name: docker-xylem
Version: 0.1.9
Summary: A docker storage plugin
Home-page: http://github.com/praekeltfoundation/docker-xylem
Author: Colin Alston
Author-email: colin@praekelt.com
License: MIT
Platform: UNKNOWN
Classifier: Development Status :: 4 - Beta
Classifier: Intended Audience :: System Administrators
Classifier: License :: OSI Approved :: MIT License
Classifier: Operating System :: POSIX
Classifier: Programming Language :: Python
Classifier: Topic :: System :: Distributed Computing
Requires-Dist: Twisted
Requires-Dist: pyyaml
